setux/distros/arch.py
setux/distros/artix.py
setux/distros/endeavour.py
setux/distros/fedora.py
setux/distros/manjaro.py
setux/distros/mint.py
setux/distros/mx.py
setux/distros/sparky.py
setux/managers/common/config/xfconf.py
setux/managers/common/package/flatpak.py
setux/managers/common/package/yay.py
setux/managers/system/package/dnf.py
setux/managers/system/package/pacman.py
setux/managers/system/service/runit.py
setux/managers/system/service/systemv.py
setux/mappings/packages_plus.py
setux/mappings/services_plus.py
setux_plus-0.2519.0.dist-info/METADATA
setux_plus-0.2519.0.dist-info/WHEEL
setux_plus-0.2519.0.dist-info/top_level.txt
setux_plus-0.2519.0.dist-info/RECORD
