Metadata-Version: 2.4
Name: setux_plus
Version: 0.2519.0
Summary: System deployment
Author-email: Louis RIVIERE <louis@riviere.xyz>
Maintainer-email: Louis RIVIERE <louis@riviere.xyz>
License: MIT
Project-URL: Homepage, https://pypi.org/project/setux-plus
Project-URL: pypi, https://pypi.org/project/setux-plus
Project-URL: repository, https://notabug.org/dugres/setux_plus
Project-URL: Documentation, https://setux-plus.readthedocs.io
Keywords: utility
Classifier: Development Status :: 3 - Alpha
Classifier: License :: OSI Approved :: MIT License
Classifier: Programming Language :: Python :: 3
Classifier: Operating System :: POSIX :: Linux
Classifier: Environment :: Console
Classifier: Intended Audience :: Developers
Classifier: Intended Audience :: Information Technology
Classifier: Intended Audience :: System Administrators
Classifier: Topic :: System :: Installation/Setup
Classifier: Topic :: System :: Systems Administration
Classifier: Topic :: Utilities
Requires-Dist: setux>=0.2511.0
